{"0":{"edges":[[[40,48],[40,632],[56,616],[56,48]],[[40,632],[456,632],[440,616],[56,616]],[[440,616],[440,56],[456,40],[456,632]],[[440,56],[48,56],[48,40],[456,40]]],"wallType":"wall"},"1":{"edges":[[[64,632],[160,632],[160,616],[64,616]]],"wallType":"coldWall"},"2":{"edges":[[[184,624],[184,384],[168,384],[168,624]]],"wallType":"wall"},"4":{"edges":[[[184,304],[184,152],[168,136],[168,304]],[[184,152],[216,152],[232,136],[168,136]],[[216,152],[216,256],[232,256],[232,136]]],"wallType":"wall"},"5":{"edges":[[[216,384],[216,464],[232,464],[232,384]]],"wallType":"wall"},"6":{"edges":[[[184,384],[184,608],[200,608],[200,384]]],"wallType":"freeDoor"},"8":{"edges":[[[344,48],[344,64],[360,64],[360,48]]],"wallType":"wall"},"9":{"edges":[[105.5,562.5]],"wallType":"start"},"10":{"edges":[[72.5,94.5]],"wallType":"finish"},"12":{"edges":[[361.5,532.5]],"wallType":"respawnFuel"},"13":{"edges":[[104.5,274.5]],"wallType":"respawnFuel"},"14":{"edges":[[390.5,206.5]],"wallType":"respawnFuel"},"16":{"edges":[[[48,152],[280,152],[296,136],[48,136]],[[280,152],[280,320],[296,320],[296,136]]],"wallType":"wall"},"18":{"edges":[[[448,152],[400,152],[400,168],[448,168]]],"wallType":"wall"},"19":{"edges":[[416,80],[128,80],[128,96],[304,96],[304,112],[128,112]],"wallType":"electricFollower"},"20":{"edges":[[48,48],[48,624],[448,624],[448,48]],"wallType":"floor"}}